generate_ast_package/__init__.py
generate_ast_package/generate_ast.py
generate_ast_aapoliakova-0.0.2.dist-info/LICENSE
generate_ast_aapoliakova-0.0.2.dist-info/METADATA
generate_ast_aapoliakova-0.0.2.dist-info/WHEEL
generate_ast_aapoliakova-0.0.2.dist-info/top_level.txt
generate_ast_aapoliakova-0.0.2.dist-info/RECORD
